a2s/__init__.py
a2s/a2s_async.py
a2s/a2s_fragment.py
a2s/a2s_sync.py
a2s/a2sasync.py
a2s/a2sfragment.py
a2s/a2sstream.py
a2s/byteio.py
a2s/datacls.py
a2s/defaults.py
a2s/exceptions.py
a2s/info.py
a2s/players.py
a2s/rules.py
python_a2s-1.3.0.dist-info/LICENSE
python_a2s-1.3.0.dist-info/METADATA
python_a2s-1.3.0.dist-info/WHEEL
python_a2s-1.3.0.dist-info/top_level.txt
python_a2s-1.3.0.dist-info/RECORD
