Metadata-Version: 2.1
Name: python-a2s
Version: 1.3.0
Summary: Query Source and GoldSource servers for name, map, players and more.
Home-page: https://github.com/Yepoleb/python-a2s
Author: Gabriel Huber
Author-email: mail@gabrielhuber.at
License: MIT License
Platform: UNKNOWN
Classifier: Development Status :: 4 - Beta
Classifier: License :: OSI Approved :: MIT License
Classifier: Programming Language :: Python :: 3
Classifier: Operating System :: OS Independent
Classifier: Topic :: Games/Entertainment
Requires-Python: >=3.7
